furrycorn/__init__.py
furrycorn/__version__.py
furrycorn/config.py
furrycorn/location.py
furrycorn/model/__init__.py
furrycorn/model/data.py
furrycorn/model/errors.py
furrycorn/model/included.py
furrycorn/model/jsonapi.py
furrycorn/model/links.py
furrycorn/model/common/__init__.py
furrycorn/model/common/meta.py
furrycorn/model/common/pagination.py
furrycorn/model/common/relationships.py
furrycorn/model/common/resource.py
furrycorn/model/common/resource_identifier.py
furrycorn/toolkit/__init__.py
furrycorn/toolkit/directory.py
furrycorn/toolkit/document.py
furrycorn/toolkit/traversal.py
furrycorn-0.7.dist-info/DESCRIPTION.rst
furrycorn-0.7.dist-info/METADATA
furrycorn-0.7.dist-info/RECORD
furrycorn-0.7.dist-info/WHEEL
furrycorn-0.7.dist-info/metadata.json
furrycorn-0.7.dist-info/top_level.txt
