Metadata-Version: 2.0
Name: furrycorn
Version: 0.7
Summary: python jsonapi parser
Home-page: https://github.com/odeumgg/furrycorn
Author: Joshua Morris
Author-email: joshua.a.morris@gmail.com
License: MIT
Platform: UNKNOWN
Classifier: Development Status :: 4 - Beta
Classifier: Intended Audience :: Developers
Classifier: License :: OSI Approved :: MIT License
Classifier: Natural Language :: English
Classifier: Operating System :: MacOS :: MacOS X
Classifier: Operating System :: POSIX
Classifier: Operating System :: Microsoft :: Windows
Classifier: Programming Language :: Python
Classifier: Programming Language :: Python :: 3.6
Classifier: Programming Language :: Python :: 3.7
Classifier: Topic :: Software Development :: Libraries
Requires-Dist: requests (>=2.18.4)
Requires-Dist: simplejson (>=3.13.2)
Requires-Dist: urllib3 (>=1.22)
